docraise/__init__.py
docraise/__main__.py
docraise/_version.py
docraise/analyzer.py
docraise/main.py
docraise/violation.py
docraise-0.1.0.dist-info/METADATA
docraise-0.1.0.dist-info/WHEEL
docraise-0.1.0.dist-info/entry_points.txt
docraise-0.1.0.dist-info/top_level.txt
docraise-0.1.0.dist-info/RECORD
