Metadata-Version: 2.1
Name: docraise
Version: 0.1.0
Summary: Docraise is a linter that checks whether the docstrings contain valid "Raises" sections
Home-page: https://github.com/Laleee/docraise
Author: Lazar Jovanovic
Author-email: jlazar1996@gmail.com
Project-URL: Source, https://github.com/Laleee/docraise
Keywords: lint
Classifier: Development Status :: 4 - Beta
Classifier: Intended Audience :: Developers
Classifier: Topic :: Software Development :: Build Tools
Classifier: Programming Language :: Python :: 3
Classifier: Programming Language :: Python :: 3.8
Classifier: Programming Language :: Python :: 3.9
Classifier: Programming Language :: Python :: 3.10
Classifier: Programming Language :: Python :: 3.11
Classifier: Programming Language :: Python :: 3 :: Only
Requires-Python: >=3.8
Requires-Dist: docstring-parser
Requires-Dist: click
